README.md
pygarn/__init__.py
pygarn/base.py
pygarn/growth.py
pygarn/old_growth.py
pygarn/shrink.py
pyproject.toml
pygarn-0.2.0.dist-info/LICENSE
pygarn-0.2.0.dist-info/WHEEL
pygarn-0.2.0.dist-info/METADATA
pygarn-0.2.0.dist-info/RECORD
