Metadata-Version: 2.1
Name: pygarn
Version: 0.2.0
Summary: 
Home-page: https://github.com/innvariant/pygarn
License: MIT
Keywords: graph operations,networkx extension,graph assembly,graph construction sequence,graph evolution
Author: Julian Stier
Author-email: julian.stier@uni-passau.de
Requires-Python: >=3.8,<4.0
Classifier: License :: OSI Approved :: MIT License
Classifier: Programming Language :: Python :: 3
Classifier: Programming Language :: Python :: 3.10
Classifier: Programming Language :: Python :: 3.8
Classifier: Programming Language :: Python :: 3.9
Requires-Dist: networkx (>=2.7.1,<3.0.0)
Project-URL: Repository, https://github.com/innvariant/pygarn
